[
  {
    "name": "01. Byakuya ~True Light~",
    "artist": "BGM",
    "url": "https://rom.831014.xyz/music/Byakuya%20~True%20Light~.m4a?v=20260112",
    "cover": "https://rom.831014.xyz/img/butterfly-icon.png"
  },
  {
    "name": "02. Dan Dan Kokoro Hikareteku",
    "artist": "BGM",
    "url": "https://rom.831014.xyz/music/Dan%20Dan%20Kokoro%20Hikareteku.m4a?v=20260112",
    "cover": "https://rom.831014.xyz/img/butterfly-icon.png"
  },
  {
    "name": "03. Don't you see!",
    "artist": "BGM",
    "url": "https://rom.831014.xyz/music/Don't%20you%20see!.m4a?v=20260112",
    "cover": "https://rom.831014.xyz/img/butterfly-icon.png"
  },
  {
    "name": "04. Kawaita Sakebi",
    "artist": "BGM",
    "url": "https://rom.831014.xyz/music/Kawaita%20Sakebi.m4a?v=20260112",
    "cover": "https://rom.831014.xyz/img/butterfly-icon.png"
  },
  {
    "name": "05. Unmei no Roulette Mawashite",
    "artist": "BGM",
    "url": "https://rom.831014.xyz/music/Unmei%20no%20Roulette%20Mawashite.m4a?v=20260112",
    "cover": "https://rom.831014.xyz/img/butterfly-icon.png"
  },
  {
    "name": "06. You Raise Me Up",
    "artist": "BGM",
    "url": "https://rom.831014.xyz/music/You%20Raise%20Me%20Up.m4a?v=20260112",
    "cover": "https://rom.831014.xyz/img/butterfly-icon.png"
  },
  {
    "name": "07. Prologue&SubtitleII",
    "artist": "BGM",
    "url": "https://rom.831014.xyz/music/Prologue%26SubtitleII.mp3?v=20260112",
    "cover": "https://rom.831014.xyz/img/butterfly-icon.png"
  },
  {
    "name": "08. You Are My Only Love",
    "artist": "王心凌",
    "url": "https://rom.831014.xyz/music/You%20Are%20My%20Only%20Love%20-%20%E7%8E%8B%E5%BF%83%E5%87%8C.mp3?v=20260112",
    "cover": "https://rom.831014.xyz/img/butterfly-icon.png"
  },
  {
    "name": "09. 丘比特的虾米",
    "artist": "林天爱",
    "url": "https://rom.831014.xyz/music/%E4%B8%98%E6%AF%94%E7%89%B9%E7%9A%84%E8%99%BE%E7%B1%B3%20-%20%E6%9E%97%E5%A4%A9%E7%88%B1.mp3?v=20260112",
    "cover": "https://rom.831014.xyz/img/butterfly-icon.png"
  },
  {
    "name": "10. 亲爱的，那不是爱情",
    "artist": "张韶涵",
    "url": "https://rom.831014.xyz/music/%E4%BA%B2%E7%88%B1%E7%9A%84%EF%BC%8C%E9%82%A3%E4%B8%8D%E6%98%AF%E7%88%B1%E6%83%85%20-%20%E5%BC%A0%E9%9F%B6%E6%B6%B5.mp3?v=20260112",
    "cover": "https://rom.831014.xyz/img/butterfly-icon.png"
  },
  {
    "name": "11. 勇气",
    "artist": "梁静茹",
    "url": "https://rom.831014.xyz/music/%E5%8B%87%E6%B0%94%20-%20%E6%A2%81%E9%9D%99%E8%8C%B9.mp3?v=20260112",
    "cover": "https://rom.831014.xyz/img/butterfly-icon.png"
  },
  {
    "name": "12. 后来",
    "artist": "刘若英",
    "url": "https://rom.831014.xyz/music/%E5%90%8E%E6%9D%A5%20-%20%E5%88%98%E8%8B%A5%E8%8B%B1.mp3?v=20260112",
    "cover": "https://rom.831014.xyz/img/butterfly-icon.png"
  },
  {
    "name": "13. 心急人上",
    "artist": "Cookies",
    "url": "https://rom.831014.xyz/music/%E5%BF%83%E6%80%A5%E4%BA%BA%E4%B8%8A%20-%20Cookies.mp3?v=20260112",
    "cover": "https://rom.831014.xyz/img/butterfly-icon.png"
  },
  {
    "name": "14. 我的秘密",
    "artist": "G.E.M. 邓紫棋",
    "url": "https://rom.831014.xyz/music/%E6%88%91%E7%9A%84%E7%A7%98%E5%AF%86%20-%20G.E.M.%20%E9%82%93%E7%B4%AB%E6%A3%8B.mp3?v=20260112",
    "cover": "https://rom.831014.xyz/img/butterfly-icon.png"
  },
  {
    "name": "15. 最后一页",
    "artist": "江语晨",
    "url": "https://rom.831014.xyz/music/%E6%9C%80%E5%90%8E%E4%B8%80%E9%A1%B5%20-%20%E6%B1%9F%E8%AF%AD%E6%99%A8.mp3?v=20260112",
    "cover": "https://rom.831014.xyz/img/butterfly-icon.png"
  },
  {
    "name": "16. 月亮代表我的心",
    "artist": "邓丽君",
    "url": "https://rom.831014.xyz/music/%E6%9C%88%E4%BA%AE%E4%BB%A3%E8%A1%A8%E6%88%91%E7%9A%84%E5%BF%83%20-%20%E9%82%93%E4%B8%BD%E5%90%9B.mp3?v=20260112",
    "cover": "https://rom.831014.xyz/img/butterfly-icon.png"
  },
  {
    "name": "17. 蒲公英的约定",
    "artist": "周杰伦",
    "url": "https://rom.831014.xyz/music/%E8%92%B2%E5%85%AC%E8%8B%B1%E7%9A%84%E7%BA%A6%E5%AE%9A%20-%20%E5%91%A8%E6%9D%B0%E4%BC%A6.mp3?v=20260112",
    "cover": "https://rom.831014.xyz/img/butterfly-icon.png"
  },
  {
    "name": "18. 街灯晚餐",
    "artist": "卫兰",
    "url": "https://rom.831014.xyz/music/%E8%A1%97%E7%81%AF%E6%99%9A%E9%A4%90%20-%20%E5%8D%AB%E5%85%B0.mp3?v=20260112",
    "cover": "https://rom.831014.xyz/img/butterfly-icon.png"
  },
  {
    "name": "19. 青春修炼手册",
    "artist": "TFBOYS",
    "url": "https://rom.831014.xyz/music/%E9%9D%92%E6%98%A5%E4%BF%AE%E7%82%BC%E6%89%8B%E5%86%8C%20-%20TFBOYS.mp3?v=20260112",
    "cover": "https://rom.831014.xyz/img/butterfly-icon.png"
  },
  {
    "name": "20. 勇气100%",
    "artist": "光GENJI",
    "url": "https://rom.831014.xyz/music/%E5%8B%87%E6%B0%97100%25%20-%20%E5%85%89GENJI.mp3?v=20260112",
    "cover": "https://rom.831014.xyz/img/butterfly-icon.png"
  },
  {
    "name": "21. Get along",
    "artist": "林原めぐみ、奥井雅美",
    "url": "https://rom.831014.xyz/music/Get%20along%20-%20%E6%9E%97%E5%8E%9F%E3%82%81%E3%81%90%E3%81%BF%E3%80%81%E5%A5%A5%E4%BA%95%E9%9B%85%E7%BE%8E.mp3?v=20260112",
    "cover": "https://rom.831014.xyz/img/butterfly-icon.png"
  },
  {
    "name": "22. Give a reason",
    "artist": "林原めぐみ",
    "url": "https://rom.831014.xyz/music/Give%20a%20reason%20-%20%E6%9E%97%E5%8E%9F%E3%82%81%E3%81%90%E3%81%BF.mp3?v=20260112",
    "cover": "https://rom.831014.xyz/img/butterfly-icon.png"
  },
  {
    "name": "23. Breeze",
    "artist": "林原めぐみ",
    "url": "https://rom.831014.xyz/music/Breeze%20-%20%E6%9E%97%E5%8E%9F%E3%82%81%E3%81%90%E3%81%BF.mp3?v=20260112",
    "cover": "https://rom.831014.xyz/img/butterfly-icon.png"
  },
  {
    "name": "24. 邪魔はさせない",
    "artist": "奥井雅美",
    "url": "https://rom.831014.xyz/music/%E9%82%AA%E9%AD%94%E3%81%AF%E3%81%95%E3%81%9B%E3%81%AA%E3%81%84%20-%20%E5%A5%A5%E4%BA%95%E9%9B%85%E7%BE%8E.mp3?v=20260112",
    "cover": "https://rom.831014.xyz/img/butterfly-icon.png"
  },
  {
    "name": "25. KUJIKENAIKARA!",
    "artist": "林原めぐみ、奥井雅美",
    "url": "https://rom.831014.xyz/music/KUJIKENAIKARA!%20-%20%E6%9E%97%E5%8E%9F%E3%82%81%E3%81%90%E3%81%BF%E3%80%81%E5%A5%A5%E4%BA%95%E9%9B%85%E7%BE%8E.mp3?v=20260112",
    "cover": "https://rom.831014.xyz/img/butterfly-icon.png"
  },
  {
    "name": "26. ～infinity～∞",
    "artist": "林原めぐみ",
    "url": "https://rom.831014.xyz/music/%EF%BD%9Einfinity%EF%BD%9E%E2%88%9E%20-%20%E6%9E%97%E5%8E%9F%E3%82%81%E3%81%90%E3%81%BF.mp3?v=20260112",
    "cover": "https://rom.831014.xyz/img/butterfly-icon.png"
  },
  {
    "name": "27. AXIA～ダイスキでダイキライ～",
    "artist": "ワルキューレ",
    "url": "https://rom.831014.xyz/music/AXIA%EF%BD%9E%E3%83%80%E3%82%A4%E3%82%B9%E3%82%AD%E3%81%A7%E3%83%80%E3%82%A4%E3%82%AD%E3%83%A9%E3%82%A4%EF%BD%9E%20-%20%E3%83%AF%E3%83%AB%E3%82%AD%E3%83%A5%E3%83%BC%E3%83%AC.mp3?v=20260112",
    "cover": "https://rom.831014.xyz/img/butterfly-icon.png"
  },
  {
    "name": "28. GIRAFFE BLUES ~Freyja Solo~",
    "artist": "鈴木みのり",
    "url": "https://rom.831014.xyz/music/GIRAFFE%20BLUES%20~Freyja%20Solo~%20-%20%E9%88%B4%E6%9C%A8%E3%81%BF%E3%81%AE%E3%82%8A.mp3?v=20260112",
    "cover": "https://rom.831014.xyz/img/butterfly-icon.png"
  },
  {
    "name": "29. いけないボーダーライン",
    "artist": "ワルキューレ",
    "url": "https://rom.831014.xyz/music/%E3%81%84%E3%81%91%E3%81%AA%E3%81%84%E3%83%9C%E3%83%BC%E3%83%80%E3%83%BC%E3%83%A9%E3%82%A4%E3%83%B3%20-%20%E3%83%AF%E3%83%AB%E3%82%AD%E3%83%A5%E3%83%BC%E3%83%AC.mp3?v=20260112",
    "cover": "https://rom.831014.xyz/img/butterfly-icon.png"
  },
  {
    "name": "30. 僕らの戦场",
    "artist": "ワルキューレ",
    "url": "https://rom.831014.xyz/music/%E5%83%95%E3%82%89%E3%81%AE%E6%88%A6%E5%A0%B4%20-%20%E3%83%AF%E3%83%AB%E3%82%AD%E3%83%A5%E3%83%BC%E3%83%AC.mp3?v=20260112",
    "cover": "https://rom.831014.xyz/img/butterfly-icon.png"
  },
  {
    "name": "31. アナタノオト",
    "artist": "中岛爱",
    "url": "https://rom.831014.xyz/music/%E3%82%A2%E3%83%8A%E3%82%BF%E3%83%8E%E3%82%AA%E3%83%88%20-%20%E4%B8%AD%E5%B3%B6%E6%84%9B.mp3?v=20260112",
    "cover": "https://rom.831014.xyz/img/butterfly-icon.png"
  },
  {
    "name": "32. ライオン",
    "artist": "May'n、中岛爱",
    "url": "https://rom.831014.xyz/music/%E3%83%A9%E3%82%A4%E3%82%AA%E3%83%B3%20-%20May'n%E3%80%81%E4%B8%AD%E5%B3%B6%E6%84%9B.mp3?v=20260112",
    "cover": "https://rom.831014.xyz/img/butterfly-icon.png"
  },
  {
    "name": "33. 娘々スペシャル服务メドレー(特盛り)",
    "artist": "May'n、中岛爱",
    "url": "https://rom.831014.xyz/music/%E5%A8%98%E3%80%85%E3%82%B9%E3%83%9A%E3%82%B7%E3%83%A3%E3%83%AB%E3%82%B5%E3%83%BC%E3%83%93%E3%82%B9%E3%83%A1%E3%83%89%E3%83%AC%E3%83%BC(%E7%89%B9%E7%9B%9B%E3%82%8A)%20-%20May'n%E3%80%81%E4%B8%AD%E5%B3%B6%E6%84%9B.mp3?v=20260112",
    "cover": "https://rom.831014.xyz/img/butterfly-icon.png"
  },
  {
    "name": "34. 星间飞行",
    "artist": "中岛爱",
    "url": "https://rom.831014.xyz/music/%E6%98%9F%E9%96%93%E9%A3%9B%E8%A1%8C%20-%20%E4%B8%AD%E5%B3%B6%E6%84%9B.mp3?v=20260112",
    "cover": "https://rom.831014.xyz/img/butterfly-icon.png"
  },
  {
    "name": "35. 突撃ラブハート",
    "artist": "Fire Bomber",
    "url": "https://rom.831014.xyz/music/%E7%AA%81%E6%92%83%E3%83%A9%E3%83%96%E3%83%8F%E3%83%BC%E3%83%88.mp3?v=20260112",
    "cover": "https://rom.831014.xyz/img/butterfly-icon.png"
  },
  {
    "name": "36. Butter-Fly",
    "artist": "和田光司",
    "url": "https://rom.831014.xyz/music/Butter-Fly%20-%20%E5%92%8C%E7%94%B0%E5%85%89%E5%8F%B8.mp3?v=20260112",
    "cover": "https://rom.831014.xyz/img/butterfly-icon.png"
  },
  {
    "name": "37. brave heart",
    "artist": "宮崎歩",
    "url": "https://rom.831014.xyz/music/brave%20heart%20-%20%E5%AE%AE%E5%B4%8E%E6%AD%A9.mp3?v=20260112",
    "cover": "https://rom.831014.xyz/img/butterfly-icon.png"
  },
  {
    "name": "38. 白夜~True Light(Full Version)",
    "artist": "Shunn",
    "url": "https://rom.831014.xyz/music/%E7%99%BD%E5%A4%9C~True%20Light(Full%20Version)%20-%20Shunn.mp3?v=20260112",
    "cover": "https://rom.831014.xyz/img/butterfly-icon.png"
  },
  {
    "name": "39. 渇いた叫び",
    "artist": "Field Of View",
    "url": "https://rom.831014.xyz/music/%E6%B8%87%E3%81%84%E3%81%9F%E5%8F%AB%E3%81%B3%20-%20Field%20Of%20View.mp3?v=20260112",
    "cover": "https://rom.831014.xyz/img/butterfly-icon.png"
  },
  {
    "name": "40. DAN DAN 心魅かれてく",
    "artist": "Field Of View",
    "url": "https://rom.831014.xyz/music/DAN%20DAN%20%E5%BF%83%E9%AD%85%E3%81%8B%E3%82%8C%E3%81%A6%E3%81%8F%20-%20Field%20Of%20View.mp3?v=20260112",
    "cover": "https://rom.831014.xyz/img/butterfly-icon.png"
  },
  {
    "name": "41. Don't you see!",
    "artist": "ZARD",
    "url": "https://rom.831014.xyz/music/Don't%20you%20see!%20-%20ZARD.mp3?v=20260112",
    "cover": "https://rom.831014.xyz/img/butterfly-icon.png"
  },
  {
    "name": "42. ハルモニア",
    "artist": "RYTHEM",
    "url": "https://rom.831014.xyz/music/%E3%83%8F%E3%83%AB%E3%83%A2%E3%83%8B%E3%82%A2%20-%20RYTHEM.mp3?v=20260112",
    "cover": "https://rom.831014.xyz/img/butterfly-icon.png"
  },
  {
    "name": "43. ブルーバード (青鸟)",
    "artist": "生物股长",
    "url": "https://rom.831014.xyz/music/%E3%83%96%E3%83%AB%E3%83%BC%E3%83%90%E3%83%BC%E3%83%89%20(%E9%9D%92%E9%B8%9F)%20-%20%E7%94%9F%E7%89%A9%E8%82%A1%E9%95%BF.mp3?v=20260112",
    "cover": "https://rom.831014.xyz/img/butterfly-icon.png"
  },
  {
    "name": "44. CLOSER",
    "artist": "井上ジョー",
    "url": "https://rom.831014.xyz/music/CLOSER%20-%20%E4%BA%95%E4%B8%8A%E3%82%B8%E3%83%A7%E3%83%BC.mp3?v=20260112",
    "cover": "https://rom.831014.xyz/img/butterfly-icon.png"
  },
  {
    "name": "45. 光と影のロマン",
    "artist": "宇徳敬子",
    "url": "https://rom.831014.xyz/music/%E5%85%89%E3%81%A8%E5%BD%B1%E3%81%AE%E3%83%AD%E3%83%9E%E3%83%B3%20-%20%E5%AE%87%E5%BE%B3%E6%95%AC%E5%AD%90.mp3?v=20260112",
    "cover": "https://rom.831014.xyz/img/butterfly-icon.png"
  },
  {
    "name": "46. 运命のルーレット廻して",
    "artist": "ZARD",
    "url": "https://rom.831014.xyz/music/%E9%81%8B%E5%91%BD%E3%81%AE%E3%83%AB%E3%83%BC%E3%83%AC%E3%83%83%E3%83%88%E5%BB%BB%E3%81%97%E3%81%A6%20-%20ZARD.mp3?v=20260112",
    "cover": "https://rom.831014.xyz/img/butterfly-icon.png"
  },
  {
    "name": "47. Bokuwa, Tori ni Naru.",
    "artist": "Hitomi",
    "url": "https://rom.831014.xyz/music/Bokuwa%2C%20Tori%20ni%20Naru.%20-%20hitomi%E3%80%81Hitomi.mp3?v=20260112",
    "cover": "https://rom.831014.xyz/img/butterfly-icon.png"
  },
  {
    "name": "48. Continued Story",
    "artist": "Hitomi",
    "url": "https://rom.831014.xyz/music/Continued%20Story%20-%20hitomi%E3%80%81Hitomi.mp3?v=20260112",
    "cover": "https://rom.831014.xyz/img/butterfly-icon.png"
  },
  {
    "name": "49. Pray",
    "artist": "Wish",
    "url": "https://rom.831014.xyz/music/Pray%20-%20Wish.mp3?v=20260112",
    "cover": "https://rom.831014.xyz/img/butterfly-icon.png"
  },
  {
    "name": "50. departure!",
    "artist": "小野正利",
    "url": "https://rom.831014.xyz/music/departure!%20-%20%E5%B0%8F%E9%87%8E%E6%AD%A3%E5%88%A9.mp3?v=20260112",
    "cover": "https://rom.831014.xyz/img/butterfly-icon.png"
  },
  {
    "name": "51. 表裏一体",
    "artist": "ゆず",
    "url": "https://rom.831014.xyz/music/%E8%A1%A8%E8%A3%8F%E4%B8%80%E4%BD%93%20-%20%E3%82%86%E3%81%9A.mp3?v=20260112",
    "cover": "https://rom.831014.xyz/img/butterfly-icon.png"
  },
  {
    "name": "52. 1/3の纯情な感情",
    "artist": "SIAM SHADE",
    "url": "https://rom.831014.xyz/music/13%E3%81%AE%E7%BA%AF%E6%83%85%E3%81%AA%E6%84%9F%E6%83%85%20-%20SIAM%20SHADE.mp3?v=20260112",
    "cover": "https://rom.831014.xyz/img/butterfly-icon.png"
  },
  {
    "name": "53. 君に触れるだけで",
    "artist": "CURIO",
    "url": "https://rom.831014.xyz/music/%E5%90%9B%E3%81%AB%E8%A7%A6%E3%82%8C%E3%82%8B%E3%81%A0%E3%81%91%E3%81%A7%20-%20CURIO.mp3?v=20260112",
    "cover": "https://rom.831014.xyz/img/butterfly-icon.png"
  },
  {
    "name": "54. 幸福になろうね",
    "artist": "佐藤朱美",
    "url": "https://rom.831014.xyz/music/%E5%B9%B8%E3%81%9B%E3%81%AB%E3%81%AA%E3%82%8D%E3%81%86%E3%81%AD.mp3?v=20260112",
    "cover": "https://rom.831014.xyz/img/butterfly-icon.png"
  },
  {
    "name": "55. BRAND NEW STORY",
    "artist": "东京劲舞娃娃",
    "url": "https://rom.831014.xyz/music/BRAND%20NEW%20STORY%20-%20%E4%B8%9C%E4%BA%AC%E5%8A%B2%E8%88%9E%E5%A8%83%E5%A8%83.mp3?v=20260112",
    "cover": "https://rom.831014.xyz/img/butterfly-icon.png"
  },
  {
    "name": "56. CHANGE THE WORLD",
    "artist": "V6",
    "url": "https://rom.831014.xyz/music/CHANGE%20THE%20WORLD%20-%20V6.mp3?v=20260112",
    "cover": "https://rom.831014.xyz/img/butterfly-icon.png"
  },
  {
    "name": "57. Depend on you",
    "artist": "浜崎あゆみ",
    "url": "https://rom.831014.xyz/music/Depend%20on%20you%20-%20%E6%B5%9C%E5%B4%8E%E3%81%82%E3%82%86%E3%81%BF.mp3?v=20260112",
    "cover": "https://rom.831014.xyz/img/butterfly-icon.png"
  },
  {
    "name": "58. Get Over",
    "artist": "Dream",
    "url": "https://rom.831014.xyz/music/Get%20Over%20-%20Dream.mp3?v=20260112",
    "cover": "https://rom.831014.xyz/img/butterfly-icon.png"
  },
  {
    "name": "59. God knows...",
    "artist": "平野綾",
    "url": "https://rom.831014.xyz/music/God%20knows...%20-%20%E5%B9%B3%E9%87%8E%E7%B6%BE.mp3?v=20260112",
    "cover": "https://rom.831014.xyz/img/butterfly-icon.png"
  },
  {
    "name": "60. I wish",
    "artist": "Reica",
    "url": "https://rom.831014.xyz/music/I%20wish-Reica%20.mp3?v=20260112",
    "cover": "https://rom.831014.xyz/img/butterfly-icon.png"
  },
  {
    "name": "61. close to you",
    "artist": "Reica",
    "url": "https://rom.831014.xyz/music/close%20to%20you-Reica.mp3?v=20260112",
    "cover": "https://rom.831014.xyz/img/butterfly-icon.png"
  },
  {
    "name": "62. Love Destiny",
    "artist": "堀江由衣",
    "url": "https://rom.831014.xyz/music/Love%20Destiny%20-%20%E5%A0%80%E6%B1%9F%E7%94%B1%E8%A1%A3.mp3?v=20260112",
    "cover": "https://rom.831014.xyz/img/butterfly-icon.png"
  },
  {
    "name": "63. Precious Memories",
    "artist": "栗林みな実",
    "url": "https://rom.831014.xyz/music/Precious%20Memories%20-%20%E6%A0%97%E6%9E%97%E3%81%BF%E3%81%AA%E5%AE%9F.mp3?v=20260112",
    "cover": "https://rom.831014.xyz/img/butterfly-icon.png"
  },
  {
    "name": "64. RAY OF LIGHT",
    "artist": "中川翔子",
    "url": "https://rom.831014.xyz/music/RAY%20OF%20LIGHT%20-%20%E4%B8%AD%E5%B7%9D%E7%BF%94%E5%AD%90.mp3?v=20260112",
    "cover": "https://rom.831014.xyz/img/butterfly-icon.png"
  },
  {
    "name": "65. “らしく”いきましょ",
    "artist": "梶谷美由紀",
    "url": "https://rom.831014.xyz/music/%E2%80%9C%E3%82%89%E3%81%97%E3%81%8F%E2%80%9D%E3%81%84%E3%81%8D%E3%81%BE%E3%81%97%E3%82%87%20-%20%E6%A2%B6%E8%B0%B7%E7%BE%8E%E7%94%B1%E7%B4%80.mp3?v=20260112",
    "cover": "https://rom.831014.xyz/img/butterfly-icon.png"
  },
  {
    "name": "66. 风も空もきっと…",
    "artist": "観月ありさ",
    "url": "https://rom.831014.xyz/music/%E9%A2%A8%E3%82%82%E7%A9%BA%E3%82%82%E3%81%8D%E3%81%A3%E3%81%A8%E2%80%A6%20-%20%E8%A6%B3%E6%9C%88%E3%81%82%E3%82%8A%E3%81%95.mp3?v=20260112",
    "cover": "https://rom.831014.xyz/img/butterfly-icon.png"
  },
  {
    "name": "67. しずく",
    "artist": "奥田美和子",
    "url": "https://rom.831014.xyz/music/%E3%81%97%E3%81%9A%E3%81%8F%20-%20%E5%A5%A5%E7%94%B0%E7%BE%8E%E5%92%8C%E5%AD%90.mp3?v=20260112",
    "cover": "https://rom.831014.xyz/img/butterfly-icon.png"
  },
  {
    "name": "68. だいじょうぶ",
    "artist": "前田亜季",
    "url": "https://rom.831014.xyz/music/%E3%81%A0%E3%81%84%E3%81%98%E3%82%87%E3%81%86%E3%81%B6%20-%20%E5%89%8D%E7%94%B0%E4%BA%9C%E5%AD%A3.mp3?v=20260112",
    "cover": "https://rom.831014.xyz/img/butterfly-icon.png"
  },
  {
    "name": "69. めざせポケモンマスター",
    "artist": "松本梨香",
    "url": "https://rom.831014.xyz/music/%E3%82%81%E3%81%96%E3%81%9B%E3%83%9D%E3%82%B1%E3%83%A2%E3%83%B3%E3%83%9E%E3%82%B9%E3%82%BF%E3%83%BC%20-%20%E6%9D%BE%E6%9C%AC%E6%A2%A8%E9%A6%99.mp3?v=20260112",
    "cover": "https://rom.831014.xyz/img/butterfly-icon.png"
  },
  {
    "name": "70. エール~あなたの梦が叶うまで",
    "artist": "WENDY",
    "url": "https://rom.831014.xyz/music/%E3%82%A8%E3%83%BC%E3%83%AB~%E3%81%82%E3%81%AA%E3%81%9F%E3%81%AE%E6%A2%A6%E3%81%8C%E5%8F%B6%E3%81%86%E3%81%BE%E3%81%A7%20-%20WENDY.mp3?v=20260112",
    "cover": "https://rom.831014.xyz/img/butterfly-icon.png"
  },
  {
    "name": "71. ペガサス幻想",
    "artist": "MAKE-UP、山田信夫",
    "url": "https://rom.831014.xyz/music/%E3%83%9A%E3%82%AC%E3%82%B5%E3%82%B9%E5%B9%BB%E6%83%B3%20-%20MAKE-UP%E3%80%81%E5%B1%B1%E7%94%B0%E4%BF%A1%E5%A4%AB.mp3?v=20260112",
    "cover": "https://rom.831014.xyz/img/butterfly-icon.png"
  },
  {
    "name": "72. 世界が終るまでは···",
    "artist": "WANDS",
    "url": "https://rom.831014.xyz/music/%E4%B8%96%E7%95%8C%E3%81%8C%E7%B5%82%E3%82%8B%E3%81%BE%E3%81%A7%E3%81%AF%C2%B7%C2%B7%C2%B7%20-%20WANDS.mp3?v=20260112",
    "cover": "https://rom.831014.xyz/img/butterfly-icon.png"
  },
  {
    "name": "73. 二人のI”s(アイズ)~i will follow~(full version)",
    "artist": "Mizuho",
    "url": "https://rom.831014.xyz/music/%E4%BA%8C%E4%BA%BA%E3%81%AEI%E2%80%9Ds(%E3%82%A2%E3%82%A4%E3%82%BA)~i%20will%20follow~(full%20version)%20-%20Mizuho.mp3?v=20260112",
    "cover": "https://rom.831014.xyz/img/butterfly-icon.png"
  },
  {
    "name": "74. 小さな翼~eyes for you~ (full version)",
    "artist": "MOKA☆",
    "url": "https://rom.831014.xyz/music/%E5%B0%8F%E3%81%95%E3%81%AA%E7%BF%BC~eyes%20for%20you~%20(full%20version)%20-%20MOKA%E2%98%86.mp3?v=20260112",
    "cover": "https://rom.831014.xyz/img/butterfly-icon.png"
  },
  {
    "name": "75. 晓の车",
    "artist": "南里侑香",
    "url": "https://rom.831014.xyz/music/%E6%9A%81%E3%81%AE%E8%BB%8A%20-%20FictionJunction%E3%80%81%E5%8D%97%E9%87%8C%E4%BE%91%E9%A6%99.mp3?v=20260112",
    "cover": "https://rom.831014.xyz/img/butterfly-icon.png"
  },
  {
    "name": "76. 爱はカッコわるい",
    "artist": "パーキッツ",
    "url": "https://rom.831014.xyz/music/%E6%84%9B%E3%81%AF%E3%82%AB%E3%83%83%E3%82%B3%E3%82%8F%E3%82%8B%E3%81%84%20-%20%E3%83%91%E3%83%BC%E3%82%AD%E3%83%83%E3%83%84.mp3?v=20260112",
    "cover": "https://rom.831014.xyz/img/butterfly-icon.png"
  },
  {
    "name": "77. 枯れない花",
    "artist": "下川みくに",
    "url": "https://rom.831014.xyz/music/%E6%9E%AF%E3%82%8C%E3%81%AA%E3%81%84%E8%8A%B1%20-%20%E4%B8%8B%E5%B7%9D%E3%81%BF%E3%81%8F%E3%81%AB.mp3?v=20260112",
    "cover": "https://rom.831014.xyz/img/butterfly-icon.png"
  },
  {
    "name": "78. 青い空に出逢えた",
    "artist": "辻尾有纱",
    "url": "https://rom.831014.xyz/music/%E9%9D%92%E3%81%84%E7%A9%BA%E3%81%AB%E5%87%BA%E9%80%A2%E3%81%88%E3%81%9F%20-%20%E8%BE%BB%E5%B0%BE%E6%9C%89%E7%BA%B1.mp3?v=20260112",
    "cover": "https://rom.831014.xyz/img/butterfly-icon.png"
  },
  {
    "name": "79. 风のように自由 ～free as the wind～",
    "artist": "宇德敬子",
    "url": "https://rom.831014.xyz/music/%E9%A2%A8%E3%81%AE%E3%82%88%E3%81%86%E3%81%AB%E8%87%AA%E7%94%B1%20%EF%BD%9Efree%20as%20the%20wind%EF%BD%9E%20-%20%E5%AE%87%E5%BE%B3%E6%95%AC%E5%AD%90.mp3?v=20260112",
    "cover": "https://rom.831014.xyz/img/butterfly-icon.png"
  },
  {
    "name": "80. KOMM, SUSSER TOD",
    "artist": "ARIANNE",
    "url": "https://rom.831014.xyz/music/KOMM%2C%20SUSSER%20TOD%20-%20ARIANNE.mp3?v=20260112",
    "cover": "https://rom.831014.xyz/img/butterfly-icon.png"
  },
  {
    "name": "81. INNOCENCE",
    "artist": "藍井エイル",
    "url": "https://rom.831014.xyz/music/INNOCENCE%20-%20%E8%97%8D%E4%BA%95%E3%82%A8%E3%82%A4%E3%83%AB.mp3?v=20260112",
    "cover": "https://rom.831014.xyz/img/butterfly-icon.png"
  },
  {
    "name": "82. crossing field",
    "artist": "LiSA",
    "url": "https://rom.831014.xyz/music/crossing%20field%20-%20LiSA.mp3?v=20260112",
    "cover": "https://rom.831014.xyz/img/butterfly-icon.png"
  },
  {
    "name": "83. 二千年... 若しくは... 二万年後の君へ・・・",
    "artist": "石川由依",
    "url": "https://rom.831014.xyz/music/%E4%BA%8C%E5%8D%83%E5%B9%B4...%20%E8%8B%A5%E3%81%97%E3%81%8F%E3%81%AF...%20%E4%BA%8C%E4%B8%87%E5%B9%B4%E5%BE%8C%E3%81%AE%E5%90%9B%E3%81%B8%E3%83%BB%E3%83%BB%E3%83%BB%20-%20Linked%20Horizon%E3%80%81%E7%9F%B3%E5%B7%9D%E7%94%B1%E4%BE%9D%E3%80%81%E6%A2%B6%E8%A3%95%E8%B2%B4.mp3?v=20260112",
    "cover": "https://rom.831014.xyz/img/butterfly-icon.png"
  }
]